promptnado/__init__.py
promptnado/core.py
promptnado/graph.py
promptnado/schemas.py
promptnado/utils.py
promptnado-0.1.0.dist-info/METADATA
promptnado-0.1.0.dist-info/WHEEL
promptnado-0.1.0.dist-info/RECORD
