Metadata-Version: 2.1
Name: promptnado
Version: 0.1.0
Summary: A framework for iterating on system prompts using evaluations
License: MIT
Author: Camron H
Author-email: camron.haider@gmail.com
Requires-Python: >=3.9.0,<3.12
Classifier: License :: OSI Approved :: MIT License
Classifier: Operating System :: OS Independent
Classifier: Programming Language :: Python :: 3
Classifier: Programming Language :: Python :: 3.9
Classifier: Programming Language :: Python :: 3.10
Classifier: Programming Language :: Python :: 3.11
Requires-Dist: langchain
Requires-Dist: langchain-openai
Requires-Dist: langgraph (>=0.1.15,<0.2.0)
Requires-Dist: langsmith
Requires-Dist: pydantic (>=1.8,<2.0)
Requires-Dist: python-dotenv
Project-URL: Bug Tracker, https://github.com/camronh/promptnado/issues
Project-URL: Homepage, https://github.com/camronh/promptnado
